{
  "contract_profile": "registryops-contract-2026-07",
  "publication_id": "phase2-000111",
  "publication_line": "phase2",
  "publication_status": "canonical",
  "published_at": "2026-07-22T14:31:10Z",
  "event_count": 590,
  "events_sha256": "f878fac6a2c8c71e382603c7d36cad75622136493ffb3823c62ff930ba22c13a",
  "merkle_root_sha256": "3bb083cce8ea0baff1efc0808deea82c4d76dbeb47b115e5f1c3df5c28e3ebd7",
  "journal_path": "journal/events.jsonl",
  "proof_status_path": "integrity/proof_status.json"
}
